openshift_client/__init__.py
openshift_client/action.py
openshift_client/ansible.py
openshift_client/apiobject.py
openshift_client/base_verbs.py
openshift_client/config.py
openshift_client/context.py
openshift_client/decorators.py
openshift_client/model.py
openshift_client/naming.py
openshift_client/result.py
openshift_client/selector.py
openshift_client/status.py
openshift_client/test_apiobject.py
openshift_client/test_model.py
openshift_client/test_selector.py
openshift_client/test_util.py
openshift_client/util.py
openshift_client-2.0.5.dist-info/LICENSE
openshift_client-2.0.5.dist-info/METADATA
openshift_client-2.0.5.dist-info/WHEEL
openshift_client-2.0.5.dist-info/top_level.txt
openshift_client-2.0.5.dist-info/RECORD
