Metadata-Version: 2.1
Name: openshift-client
Version: 2.0.5
Summary: OpenShift python client
Author-email: Justin Pierce <jupierce@redhat.com>
Maintainer-email: Brad Williams <brawilli@redhat.com>
License: 
Project-URL: Homepage, https://github.com/openshift/openshift-client-python
Project-URL: Issues, https://github.com/openshift/openshift-client-python/issues
Keywords: OpenShift
Classifier: Development Status :: 4 - Beta
Classifier: Intended Audience :: Developers
Classifier: Intended Audience :: Information Technology
Classifier: License :: OSI Approved :: Apache Software License
Classifier: Operating System :: OS Independent
Classifier: Programming Language :: Python
Classifier: Programming Language :: Python :: 3
Classifier: Programming Language :: Python :: 3.12
Classifier: Topic :: Utilities
Requires-Python: >=3.0
License-File: LICENSE
Requires-Dist: build
Requires-Dist: six
Requires-Dist: pyyaml
Provides-Extra: ssh
Requires-Dist: paramiko; extra == "ssh"
